{"data":[{"id":"111668955554282","name":"\uc0bc\uc131 (Samsung)","picture":{"data":{"is_silhouette":false,"url":"https:\/\/scontent.xx.fbcdn.net\/hprofile-xft1\/v\/t1.0-1\/p100x100\/12814762_958462750874894_3552725840403889813_n.png?oh=39a8ddda02d16bd7a493b4611cd983f0&oe=578304B3"}},"likes":3081933},{"id":"114219621960016","name":"Samsung Mobile","picture":{"data":{"is_silhouette":false,"url":"https:\/\/scontent.xx.fbcdn.net\/hprofile-xla1\/v\/t1.0-1\/p100x100\/11071590_838711186177519_5497080331647333793_n.jpg?oh=14247d9d88f42a44007c4a6896968a28&oe=578F26CF"}},"likes":42364929},{"id":"136805923037665","name":"Samsung Egypt","picture":{"data":{"is_silhouette":false,"url":"https:\/\/scontent.xx.fbcdn.net\/hprofile-xfa1\/v\/t1.0-1\/p100x100\/10996996_901701229881460_7653196121974123_n.jpg?oh=86eeb5cbf4334a4b951d61b0733fc40f&oe=57812BD3"}},"likes":8008196},{"id":"123846607777417","name":"Samsung Georgia","picture":{"data":{"is_silhouette":false,"url":"https:\/\/scontent.xx.fbcdn.net\/hprofile-xaf1\/v\/t1.0-1\/p100x100\/11050807_427605644068177_2676992945614185492_n.png?oh=1311c4aee3ca5d5e23835bfd96dd2cd7&oe=5796785B"}},"likes":196582},{"id":"160097297433507","name":"Samsung Paraguay","picture":{"data":{"is_silhouette":false,"url":"https:\/\/scontent.xx.fbcdn.net\/hprofile-xtp1\/v\/t1.0-1\/p100x100\/12019982_779792962130601_2852602540481813322_n.png?oh=c4a454303b8c8da1dd7b8487ed5de564&oe=579488F4"}},"likes":184886},{"id":"407862499912","name":"Samsung Portugal","picture":{"data":{"is_silhouette":false,"url":"https:\/\/scontent.xx.fbcdn.net\/hprofile-xat1\/v\/t1.0-1\/p100x100\/12119104_10153708772119913_7909359410835055572_n.png?oh=b907408ca4fd3184e36ff8c31e84fd04&oe=577E62A4"}},"likes":1083608}],"paging":{"cursors":{"before":"MAZDZD","after":"NQZDZD"},"next":"https:\/\/graph.facebook.com\/v2.5\/search?access_token=256301091132754%7Cc_Ex2RAB3BHe76-W8e_zKd3rn6w&fields=id%2Cname%2Cpicture.type%28normal%29%2Clikes&q=samsung&type=page&limit=6&after=NQZDZD"}}